[
  {
    "id": 1,
    "title": "E-Commerce Platform",
    "description_az": "Tam funksional e-ticarət platforması",
    "description_en": "Full-featured e-commerce platform",
    "description_ru": "Полнофункциональная платформа электронной коммерции",
    "image": "/images/project1.jpg",
    "tags": ["React", "Next.js", "PostgreSQL", "Tailwind"],
    "category": "fullstack",
    "url": "https://example.com",
    "github": "https://github.com/turanly/project1",
    "featured": true
  },
  {
    "id": 2,
    "title": "Task Manager App",
    "description_az": "Modern task idarəetmə tətbiqi",
    "description_en": "Modern task management application",
    "description_ru": "Современное приложение для управления задачами",
    "image": "/images/project2.jpg",
    "tags": ["React", "TypeScript", "Node.js", "MongoDB"],
    "category": "fullstack",
    "url": "https://example.com",
    "github": "https://github.com/turanly/project2",
    "featured": true
  },
  {
    "id": 3,
    "title": "Portfolio Website",
    "description_az": "Şəxsi portfolio saytı",
    "description_en": "Personal portfolio website",
    "description_ru": "Личный сайт-портфолио",
    "image": "/images/project3.jpg",
    "tags": ["Next.js", "Tailwind", "Framer Motion"],
    "category": "frontend",
    "url": "https://turanly.com",
    "github": "https://github.com/turanly/turanly",
    "featured": true
  },
  {
    "id": 4,
    "title": "Weather Dashboard",
    "description_az": "Real-time hava məlumatları paneli",
    "description_en": "Real-time weather dashboard",
    "description_ru": "Панель погоды в реальном времени",
    "image": "/images/project4.jpg",
    "tags": ["React", "API", "Chart.js", "CSS"],
    "category": "frontend",
    "url": "https://example.com",
    "github": "https://github.com/turanly/project4",
    "featured": false
  },
  {
    "id": 5,
    "title": "Chat Application",
    "description_az": "Real-time chat tətbiqi",
    "description_en": "Real-time chat application",
    "description_ru": "Приложение чата в реальном времени",
    "image": "/images/project5.jpg",
    "tags": ["React", "Socket.io", "Node.js", "Redis"],
    "category": "fullstack",
    "url": "https://example.com",
    "github": "https://github.com/turanly/project5",
    "featured": false
  }
]
